{
  "gitSyncId": "66ab8acc0328fd3f694dbfdc_a6324648-a0c2-4c0b-b921-ddf1ccd704f4",
  "id": "Page1_JSModule13",
  "moduleUUID": "d2aed24a-ea00-4859-8287-13335173a9fa",
  "packageUUID": "26adfd9e-4ae4-48e6-b340-0e3a5b0e400d",
  "type": "JS_MODULE",
  "unpublishedModuleInstance": {
    "contextType": "PAGE",
    "inputs": {
      "myFun1": "[\"{{11}}\",\"{{22}}\"]",
      "myFun2": "[]"
    },
    "moduleInputs": {
      "cpfpkkdsiz": {},
      "yrmanbxntz": {}
    },
    "name": "JSModule13",
    "pageId": "Page1",
    "version": "0.0.8"
  }
}